ghexplain/__init__.py
ghexplain/cli.py
ghexplain/core.py
ghexplain/exceptions.py
ghexplain-0.0.3.dist-info/LICENSE
ghexplain-0.0.3.dist-info/METADATA
ghexplain-0.0.3.dist-info/WHEEL
ghexplain-0.0.3.dist-info/entry_points.txt
ghexplain-0.0.3.dist-info/top_level.txt
ghexplain-0.0.3.dist-info/RECORD
