Metadata-Version: 2.1
Name: ghexplain
Version: 0.0.3
Summary: AI-powered explanations for GitHub issues using LangChain
Author-email: Stefano Fancello <stefano.fancello@nethesis.it>
Project-URL: Homepage, https://github.com/Stell0/ghexplain
Project-URL: Bug Tracker, https://github.com/Stell0/ghexplain/issues
Classifier: Programming Language :: Python :: 3
Classifier: License :: OSI Approved :: GNU Affero General Public License v3
Classifier: Operating System :: OS Independent
Requires-Python: >=3.8
License-File: LICENSE
Requires-Dist: langchain>=0.3.0
Requires-Dist: langchain-openai>=0.2.0
Requires-Dist: requests>=2.32.3
Requires-Dist: python-dotenv>=1.0.0
